co2sys/__init__.py
co2sys/core.py
co2sys/tests/__init__.py
co2sys/tests/test_core.py
co2syspy-0.0.1a0.dist-info/DESCRIPTION.rst
co2syspy-0.0.1a0.dist-info/METADATA
co2syspy-0.0.1a0.dist-info/RECORD
co2syspy-0.0.1a0.dist-info/WHEEL
co2syspy-0.0.1a0.dist-info/metadata.json
co2syspy-0.0.1a0.dist-info/top_level.txt
